ab_test.py
cli.py
setup.py
bayesian_ab_test.egg-info/PKG-INFO
bayesian_ab_test.egg-info/SOURCES.txt
bayesian_ab_test.egg-info/dependency_links.txt
bayesian_ab_test.egg-info/entry_points.txt
bayesian_ab_test.egg-info/not-zip-safe
bayesian_ab_test.egg-info/requires.txt
bayesian_ab_test.egg-info/top_level.txt